astrodust/__init__.py
astrodust/astrodust.py
dustyforest/__init__.py
dustyforest/dustyforest.py
astrodust-1.0.0.dist-info/LICENSE
astrodust-1.0.0.dist-info/METADATA
astrodust-1.0.0.dist-info/WHEEL
astrodust-1.0.0.dist-info/top_level.txt
astrodust-1.0.0.dist-info/RECORD
