Metadata-Version: 2.1
Name: astrodust
Version: 1.0.0
Summary: A library for predicting the distribution of dust particles in protoplanetary disks
Home-page: https://github.com/kehoffman3/astrodust
Author: UVA Astronomy Capstone Group
Author-email: keh4nb@virginia.edu
License: UNKNOWN
Keywords: astronomy,machine learning,planets,random forest
Platform: UNKNOWN
Classifier: Intended Audience :: Developers
Classifier: Topic :: Software Development :: Build Tools
Classifier: License :: OSI Approved :: MIT License
Classifier: Programming Language :: Python :: 3
Classifier: Programming Language :: Python :: 3.6
Classifier: Programming Language :: Python :: 3.7
Classifier: Programming Language :: Python :: 3.8
Classifier: Programming Language :: Python :: 3.9
Classifier: Programming Language :: Python :: 3 :: Only
Requires-Python: >=3.6, <4
Requires-Dist: joblib (>=1.0)
Requires-Dist: xgboost (>=1.2)
Requires-Dist: tqdm (>=4.50)
Requires-Dist: scikit-learn (>=0.24.0)
